Metadata-Version: 2.1
Name: snirf-quality-report
Version: 0.0.13
Summary: Get fNIRS SNIRF raw data quality report
Home-page: https://github.com/BUNPC/snirf_quality_report
Author: SK
Author-email: skura@bu.edu
License: MIT
Platform: UNKNOWN
Classifier: License :: OSI Approved :: MIT License
Classifier: Programming Language :: Python
Classifier: Programming Language :: Python :: 3
Classifier: Programming Language :: Python :: 3.7
Classifier: Programming Language :: Python :: Implementation :: CPython
Classifier: Programming Language :: Python :: Implementation :: PyPy
Requires-Python: >=3.7.5
